pyopenie/__init__.py
pyopenie/openie.py
pyopenie-0.2.0.dist-info/LICENSE
pyopenie-0.2.0.dist-info/METADATA
pyopenie-0.2.0.dist-info/WHEEL
pyopenie-0.2.0.dist-info/top_level.txt
pyopenie-0.2.0.dist-info/RECORD
