Metadata-Version: 2.1
Name: pyopenie
Version: 0.2.0
Summary: Python wrapper for OpenIE5
Home-page: https://github.com/vaibhavad/python-wrapper-OpenIE5
Author: Vaibhav Adlakha
Author-email: vaibhavadlakha95@gmail.com
License: UNKNOWN
Keywords: nlp
Platform: UNKNOWN
Requires-Dist: requests
